[
  {
    "token": "FLOKI",
    "address": "0xcf0c122c6b73ff809c693db761e7baebe62b6a2e",
    "signal": "HOLD",
    "confidence": 0.82,
    "price": 0.09646312,
    "volume_24h": 115326.7,
    "price_change_24h": 21.58,
    "timestamp": "2026-04-17T07:09:00.621715"
  },
  {
    "token": "WOJAK",
    "address": "0x5026f006b85729a8b14553fae6af249ad16c9aab",
    "signal": "BUY",
    "confidence": 0.79,
    "price": 0.0669645,
    "volume_24h": 4383761.23,
    "price_change_24h": -10.97,
    "timestamp": "2026-04-17T07:09:00.621699"
  },
  {
    "token": "PEPE",
    "address": "0x6982508145454ce325ddbe47a25d4ec3d2311933",
    "signal": "HOLD",
    "confidence": 0.73,
    "price": 0.09562817,
    "volume_24h": 4483705.29,
    "price_change_24h": 18.49,
    "timestamp": "2026-04-17T07:09:00.621687"
  },
  {
    "token": "DOGE2",
    "address": "0xba8a621b4a54e61c442f5ec623687e2a942225ef",
    "signal": "HOLD",
    "confidence": 0.7,
    "price": 0.08739237,
    "volume_24h": 2127832.82,
    "price_change_24h": 5.74,
    "timestamp": "2026-04-17T07:09:00.621708"
  },
  {
    "token": "SHIB",
    "address": "0x95ad61b0a150d79219dcf64e1e6cc01f0b64c4ce",
    "signal": "HOLD",
    "confidence": 0.67,
    "price": 0.015255,
    "volume_24h": 1410387.83,
    "price_change_24h": 0.13,
    "timestamp": "2026-04-17T07:09:00.621722"
  }
]