[
  {
    "token": "DOGE2",
    "address": "0xba8a621b4a54e61c442f5ec623687e2a942225ef",
    "signal": "HOLD",
    "confidence": 0.86,
    "price": 0.08648476,
    "volume_24h": 313264.47,
    "price_change_24h": 9.72,
    "timestamp": "2026-04-02T22:27:15.763616"
  },
  {
    "token": "FLOKI",
    "address": "0xcf0c122c6b73ff809c693db761e7baebe62b6a2e",
    "signal": "HOLD",
    "confidence": 0.85,
    "price": 0.08155594,
    "volume_24h": 2703584.91,
    "price_change_24h": -4.94,
    "timestamp": "2026-04-02T22:27:15.763627"
  },
  {
    "token": "PEPE",
    "address": "0x6982508145454ce325ddbe47a25d4ec3d2311933",
    "signal": "BUY",
    "confidence": 0.85,
    "price": 0.07669347,
    "volume_24h": 562229.25,
    "price_change_24h": -5.87,
    "timestamp": "2026-04-02T22:27:15.763642"
  },
  {
    "token": "SHIB",
    "address": "0x95ad61b0a150d79219dcf64e1e6cc01f0b64c4ce",
    "signal": "BUY",
    "confidence": 0.78,
    "price": 0.04437519,
    "volume_24h": 4199470.8,
    "price_change_24h": -10.23,
    "timestamp": "2026-04-02T22:27:15.763635"
  }
]