[
  {
    "token": "PEPE",
    "address": "0x6982508145454ce325ddbe47a25d4ec3d2311933",
    "signal": "HOLD",
    "confidence": 0.84,
    "price": 0.0375424,
    "volume_24h": 2164549.01,
    "price_change_24h": 5.85,
    "timestamp": "2026-03-22T09:02:58.544412"
  },
  {
    "token": "FLOKI",
    "address": "0xcf0c122c6b73ff809c693db761e7baebe62b6a2e",
    "signal": "SELL",
    "confidence": 0.81,
    "price": 0.05442434,
    "volume_24h": 559423.95,
    "price_change_24h": 1.94,
    "timestamp": "2026-03-22T09:02:58.544404"
  },
  {
    "token": "WOJAK",
    "address": "0x5026f006b85729a8b14553fae6af249ad16c9aab",
    "signal": "HOLD",
    "confidence": 0.69,
    "price": 0.06193406,
    "volume_24h": 2489115.26,
    "price_change_24h": 10.68,
    "timestamp": "2026-03-22T09:02:58.544419"
  }
]