[
  {
    "token": "PEPE",
    "address": "0x6982508145454ce325ddbe47a25d4ec3d2311933",
    "signal": "SELL",
    "confidence": 0.84,
    "price": 0.09862818,
    "volume_24h": 2109260.77,
    "price_change_24h": 22.83,
    "timestamp": "2026-05-17T14:02:03.610353"
  },
  {
    "token": "FLOKI",
    "address": "0xcf0c122c6b73ff809c693db761e7baebe62b6a2e",
    "signal": "HOLD",
    "confidence": 0.75,
    "price": 0.04262958,
    "volume_24h": 1557870.32,
    "price_change_24h": -4.25,
    "timestamp": "2026-05-17T14:02:03.610338"
  },
  {
    "token": "SHIB",
    "address": "0x95ad61b0a150d79219dcf64e1e6cc01f0b64c4ce",
    "signal": "BUY",
    "confidence": 0.7,
    "price": 0.04204913,
    "volume_24h": 3292965.39,
    "price_change_24h": 1.64,
    "timestamp": "2026-05-17T14:02:03.610346"
  }
]